vibegit/__init__.py
vibegit/ai.py
vibegit/cli.py
vibegit/config.py
vibegit/git.py
vibegit/llm.py
vibegit/prompts.py
vibegit/schemas.py
vibegit/utils.py
vibegit/wizard.py
vibegit-0.2.0.dist-info/licenses/LICENSE
vibegit-0.2.0.dist-info/METADATA
vibegit-0.2.0.dist-info/WHEEL
vibegit-0.2.0.dist-info/entry_points.txt
vibegit-0.2.0.dist-info/top_level.txt
vibegit-0.2.0.dist-info/RECORD
