Metadata-Version: 2.4
Name: vibegit
Version: 0.2.0
Summary: Automagically group and commit semantically related changes in your Git repository with AI.
Requires-Python: >=3.11
License-File: LICENSE
Requires-Dist: click>=8.1.8
Requires-Dist: diff-parser>=1.1
Requires-Dist: gitpython>=3.1.44
Requires-Dist: inquirer>=3.4.0
Requires-Dist: platformdirs>=4.3.7
Requires-Dist: pydantic-ai
Requires-Dist: pydantic>=2.11.3
Requires-Dist: pydantic-settings>=2.9.1
Requires-Dist: python-dotenv>=1.1.0
Requires-Dist: rich>=14.0.0
Requires-Dist: toml>=0.10.2
Requires-Dist: unidiff>=0.7.5
Dynamic: license-file
